README.rst
setup.py
KettleParser/__init__.py
KettleParser.egg-info/PKG-INFO
KettleParser.egg-info/SOURCES.txt
KettleParser.egg-info/dependency_links.txt
KettleParser.egg-info/top_level.txt
tests/KettleParserTests.py
tests/__init__.py
tests/constants.py