Metadata-Version: 1.1
Name: KettleParser
Version: 1.0.1
Summary: Library for parsing and analyzing Kettle XML files
Home-page: https://github.com/graphiq-data/KettleParser
Author: Jeff Portwood - Graphiq Data Engineering
Author-email: jportwood@graphiq.com
License: MIT
Keywords: kettle pdi pentaho
Platform: UNKNOWN
Classifier: Development Status :: 3 - Alpha
Classifier: Intended Audience :: Developers
Classifier: License :: OSI Approved :: MIT License
Classifier: Programming Language :: Python :: 2
Classifier: Programming Language :: Python :: 2.7
Classifier: Programming Language :: Python :: 3
